django_user_settings-0.0.12.dist-info/DESCRIPTION.rst
django_user_settings-0.0.12.dist-info/METADATA
django_user_settings-0.0.12.dist-info/RECORD
django_user_settings-0.0.12.dist-info/WHEEL
django_user_settings-0.0.12.dist-info/metadata.json
django_user_settings-0.0.12.dist-info/top_level.txt
user_settings/__init__.py
user_settings/admin.py
user_settings/apps.py
user_settings/models.py
user_settings/tests.py
user_settings/utils.py
user_settings/views.py
user_settings/migrations/0001_initial.py
user_settings/migrations/0002_auto_20181120_1055.py
user_settings/migrations/0003_auto_20181225_1022.py
user_settings/migrations/__init__.py
