Metadata-Version: 2.0
Name: django-user-settings
Version: 0.0.12
Summary: Enable settings for each user
Home-page: https://app.lucidfoundry.com/lc-community/django-user-setting.git
Author: viethq.lucidfoundry
Author-email: viet.hoang@lucidfoundry.com
License: UNKNOWN
Platform: UNKNOWN
Classifier: Environment :: Web Environment
Classifier: Framework :: Django
Classifier: Framework :: Django :: 2.0
Classifier: Intended Audience :: Developers
Classifier: License :: OSI Approved :: BSD License
Classifier: Operating System :: OS Independent
Classifier: Programming Language :: Python
Classifier: Programming Language :: Python :: 3.5
Classifier: Programming Language :: Python :: 3.6
Classifier: Topic :: Internet :: WWW/HTTP
Classifier: Topic :: Internet :: WWW/HTTP :: Dynamic Content
